demux_1_8.v
module always_1_8demux(in,s,y);
input in;
input [2:0] s;
output [7:0] y;
reg y;

always @ (s or in)
begin
if(in == 0)
      y = 8'b0;
else
case(s)
0 :      y = 8'b00000001;
1 :      y = 8'b00000010;
2 :      y = 8'b00000100;
3 :      y = 8'b00001000;
4 :      y = 8'b00010000;
5 :      y = 8'b00100000;
6 :      y = 8'b01000000;
7 :      y = 8'b10000000;

endcase
end
endmodule

test_demux_1_8.v
module test_1_8demux();
reg inbit;
reg [2:0] sbit;
wire [7:0] ybit;

always_1_8demux obj(
.in(inbit),
.s(sbit),
.y(ybit)
);

initial begin
      inbit = 0;  sbit = 3'bxxx;
      #10;      inbit = 1;  sbit = 3'b000;
      #10;      inbit = 1;  sbit = 3'b001;
      #10;      inbit = 1;  sbit = 3'b010;
      #10;      inbit = 1;  sbit = 3'b011;
      #10;      inbit = 1;  sbit = 3'b100;
      #10;      inbit = 1;  sbit = 3'b101;
      #10;      inbit = 1;  sbit = 3'b110;
      #10;      inbit = 1;  sbit = 3'b111;
#20;
end

initial
  begin
    $dumpfile("always_1_8_demux.vcd");
    $dumpvars(0,test_1_8demux);
    $monitor("time = %2d,   INPUT=%1b,     S3S2S1 =%3b,    OUT =%8b", $time,inbit,sbit,ybit);
  end
endmodule

always_1_8_demux.vcd
$date
	Thu Sep 27 16:36:18 2018
$end
$version
	Icarus Verilog
$end
$timescale
	1s
$end
$scope module test_1_8demux $end
$var wire 8 ! ybit [7:0] $end
$var reg 1 " inbit $end
$var reg 3 # sbit [2:0] $end
$scope module obj $end
$var wire 1 " in $end
$var wire 3 $ s [2:0] $end
$var reg 8 % y [7:0] $end
$upscope $end
$upscope $end
$enddefinitions $end
#0
$dumpvars
b0 %
bx $
bx #
0"
b0 !
$end
#10
b1 !
b1 %
b0 #
b0 $
1"
#20
b10 !
b10 %
b1 #
b1 $
#30
b100 !
b100 %
b10 #
b10 $
#40
b1000 !
b1000 %
b11 #
b11 $
#50
b10000 !
b10000 %
b100 #
b100 $
#60
b100000 !
b100000 %
b101 #
b101 $
#70
b1000000 !
b1000000 %
b110 #
b110 $
#80
b10000000 !
b10000000 %
b111 #
b111 $
