always_8_1mux.v
module always_8_1mux(in,s,y);

input [7:0] in;
input [2:0] s;
output y;
reg y;

always @ (s or in or y)
begin
if(in == 8'b00000000) begin
      y = 0;
end
else begin
case(s)
0 :      y = in[0];
1 :      y = in[1];
2 :      y = in[2];
3 :      y = in[3];
4 :      y = in[4];
5 :      y = in[5];
6 :      y = in[6];
7 :      y = in[7];

endcase
end
end
endmodule

test_always_8_1mux.v
module test_8_1mux();
reg [7:0] inbit;
reg [2:0] sbit;
wire ybit;

always_8_1mux obj(
.in(inbit),
.s(sbit),
.y(ybit)
);

initial begin
      inbit = 8'b00000000;  sbit = 3'bxxx;
      #10;      inbit = 8'b00000001;  sbit = 3'b000;
      #10;      inbit = 8'b00000010;  sbit = 3'b001;
      #10;      inbit = 8'b00000100;  sbit = 3'b010;
      #10;      inbit = 8'b00001000;  sbit = 3'b011;
      #10;      inbit = 8'b00010000;  sbit = 3'b100;
      #10;      inbit = 8'b00100000;  sbit = 3'b101;
      #10;      inbit = 8'b01000000;  sbit = 3'b110;
      #10;      inbit = 8'b10000000;  sbit = 3'b111;
#20;
end

initial
  begin
    $dumpfile("always_8_1_mux.vcd");
    $dumpvars(0,test_8_1mux);
    $monitor("time = %2d,   INPUT=%8b,     S3S2S1 =%3b,    OUT =%1b", $time,inbit,sbit,ybit);
  end
endmodule

always_8_1_mux.vcd
$date
	Thu Sep 27 16:31:42 2018
$end
$version
	Icarus Verilog
$end
$timescale
	1s
$end
$scope module test_8_1mux $end
$var wire 1 ! ybit $end
$var reg 8 " inbit [7:0] $end
$var reg 3 # sbit [2:0] $end
$scope module obj $end
$var wire 8 $ in [7:0] $end
$var wire 3 % s [2:0] $end
$var reg 1 ! y $end
$upscope $end
$upscope $end
$enddefinitions $end
#0
$dumpvars
bx %
b0 $
bx #
b0 "
0!
$end
#10
1!
b0 #
b0 %
b1 "
b1 $
#20
b1 #
b1 %
b10 "
b10 $
#30
b10 #
b10 %
b100 "
b100 $
#40
b11 #
b11 %
b1000 "
b1000 $
#50
b100 #
b100 %
b10000 "
b10000 $
#60
b101 #
b101 %
b100000 "
b100000 $
#70
b110 #
b110 %
b1000000 "
b1000000 $
#80
b111 #
b111 %
b10000000 "
b10000000 $
