cmos_mux_2_1.v
module mux_2_1(input a, input b, input s, output y);
supply0 gnd;
supply1 vdd;
wire w1,w2,w3;

pmos(w1,vdd,s);
pmos(y,w1,~a);
pmos(w2,vdd,~s);
pmos(y,w2,~b);

nmos(y,w3,~a);
nmos(y,w3,s);
nmos(w3,gnd,~b);
nmos(w3,gnd,~s);
endmodule

cmos_mux_4_1.v
`include "cmos_mux_2_1.v"

module mux_4_1(input a, input b, input c, input d, input s0, input s1, output y);
wire w1,w2;
mux_2_1 o1(.a(a),.b(b),.s(s0),.y(w1));
mux_2_1 o2(.a(c),.b(d),.s(s0),.y(w2));
mux_2_1 o3(.a(w1),.b(w2),.s(s1),.y(y));

endmodule

cmos_mux_4_1_tb.v
module test_4_1mux();

reg abit;
reg bbit;
reg cbit;
reg dbit;
reg sel0;
reg sel1;
wire w;

mux_4_1 obj(
.a(abit),
.b(bbit),
.c(cbit),
.d(dbit),
.s0(sel0),
.s1(sel1),
.y(w)
);

initial
      begin
            sel0=0;     sel1=0;     abit=0;     bbit=0;     cbit=1;     dbit=1;
            #10;        sel0=0;     sel1=0;          abit=0; bbit=1; cbit=0; dbit=1;
            #10;        sel0=1;     sel1=0;          abit=0; bbit=0; cbit=1; dbit=1;
            #10;        sel0=1;     sel1=0;          abit=0; bbit=1; cbit=0; dbit=1;
            #10;        sel0=0;     sel1=1;          abit=0; bbit=0; cbit=1; dbit=1;
            #10;        sel0=0;     sel1=1;          abit=0; bbit=1; cbit=0; dbit=1;
            #10;        sel0=1;     sel1=1;          abit=0; bbit=0; cbit=1; dbit=1;
            #10;        sel0=1;     sel1=1;          abit=0; bbit=1; cbit=0; dbit=1;
            #20;
      end

initial
  begin
    $dumpfile("cmos_mux_4_1.vcd");
    $dumpvars(0,test_4_1mux);
    $monitor("time = %2d,      S1(MSB) =%1b, S0 =%1b      A =%1b,   B =%1b,   C =%1b,    D =%1b,    Out =%1b", $time,sel1,sel0,abit,bbit,cbit,dbit,w);
  end
endmodule

cmos_mux_4_1.vcd
$date
	Thu Sep 20 16:16:31 2018
$end
$version
	Icarus Verilog
$end
$timescale
	1s
$end
$scope module test_4_1mux $end
$var wire 1 ! w $end
$var reg 1 " abit $end
$var reg 1 # bbit $end
$var reg 1 $ cbit $end
$var reg 1 % dbit $end
$var reg 1 & sel0 $end
$var reg 1 ' sel1 $end
$scope module obj $end
$var wire 1 " a $end
$var wire 1 # b $end
$var wire 1 $ c $end
$var wire 1 % d $end
$var wire 1 & s0 $end
$var wire 1 ' s1 $end
$var wire 1 ( w1 $end
$var wire 1 ) w2 $end
$var wire 1 ! y $end
$scope module o1 $end
$var wire 1 " a $end
$var wire 1 # b $end
$var wire 1 * gnd $end
$var wire 1 & s $end
$var wire 1 + vdd $end
$var wire 1 , w1 $end
$var wire 1 - w2 $end
$var wire 1 . w3 $end
$var wire 1 ( y $end
$upscope $end
$scope module o2 $end
$var wire 1 $ a $end
$var wire 1 % b $end
$var wire 1 / gnd $end
$var wire 1 & s $end
$var wire 1 0 vdd $end
$var wire 1 1 w1 $end
$var wire 1 2 w2 $end
$var wire 1 3 w3 $end
$var wire 1 ) y $end
$upscope $end
$scope module o3 $end
$var wire 1 ( a $end
$var wire 1 ) b $end
$var wire 1 4 gnd $end
$var wire 1 ' s $end
$var wire 1 5 vdd $end
$var wire 1 6 w1 $end
$var wire 1 7 w2 $end
$var wire 1 8 w3 $end
$var wire 1 ! y $end
$upscope $end
$upscope $end
$upscope $end
$enddefinitions $end
#0
$dumpvars
08
z7
16
15
04
03
z2
11
10
0/
0.
z-
1,
1+
0*
1)
0(
0'
0&
1%
1$
0#
0"
0!
$end
#10
0)
0$
1#
#20
1-
0(
0.
12
1)
z3
1$
0#
z,
z1
1&
#30
1!
1(
z.
0$
1#
#40
17
z8
z-
0(
0.
z2
1)
03
1$
0#
z6
1!
1'
1,
11
0&
#50
0!
08
0)
0$
1#
#60
1!
z8
1-
0(
0.
12
1)
z3
1$
0#
z,
z1
1&
#70
1(
z.
0$
1#
