cmos_mux_2_1.v
module mux_2_1(input a, input b, input s, output y);
supply0 gnd;
supply1 vdd;
wire w1,w2,w3;

pmos(w1,vdd,s);
pmos(y,w1,~a);
pmos(w2,vdd,~s);
pmos(y,w2,~b);

nmos(y,w3,~a);
nmos(y,w3,s);
nmos(w3,gnd,~b);
nmos(w3,gnd,~s);
endmodule

cmos_mux_2_1_tb.v
module test_2_1mux();

reg abit;
reg bbit;
wire w;
reg sel;

mux_2_1 obj(
.a(abit),
.b(bbit),
.s(sel),
.y(w)
);

initial
      begin
            abit=0;
            bbit=0;
            sel=0;
            #10;        sel=0;          abit=0; bbit=1;
            #10;        sel=0;          abit=1; bbit=0;
            #10;        sel=0;          abit=1; bbit=1;
            #10;        sel=1;          abit=0; bbit=0;
            #10;        sel=1;          abit=1; bbit=0;
            #10;        sel=1;          abit=0; bbit=1;
            #10;        sel=1;          abit=1; bbit=1;
            #20;
      end

initial
  begin
    $dumpfile("cmos_mux_2_1.vcd");
    $dumpvars(0,test_2_1mux);
    $monitor("time = %2d,      S =%1b,       A =%1b,   B =%1b,    Out =%1b", $time,sel,abit,bbit,w);
  end
endmodule

cmos_mux_2_1.vcd
$date
	Thu Sep 20 16:16:10 2018
$end
$version
	Icarus Verilog
$end
$timescale
	1s
$end
$scope module test_2_1mux $end
$var wire 1 ! w $end
$var reg 1 " abit $end
$var reg 1 # bbit $end
$var reg 1 $ sel $end
$scope module obj $end
$var wire 1 " a $end
$var wire 1 # b $end
$var wire 1 % gnd $end
$var wire 1 $ s $end
$var wire 1 & vdd $end
$var wire 1 ' w1 $end
$var wire 1 ( w2 $end
$var wire 1 ) w3 $end
$var wire 1 ! y $end
$upscope $end
$upscope $end
$enddefinitions $end
#0
$dumpvars
0)
z(
1'
1&
0%
0$
0#
0"
0!
$end
#10
1#
#20
1!
0#
1"
#30
1#
#40
1(
0)
0#
0"
z'
0!
1$
#50
1"
#60
1!
z)
1#
0"
#70
1"
