ternary_mux.v
module ternary_mux(in,s,y);
input [1:0] in;
input s;
output y;

assign y = s==0 ? in[0] : in[1];
endmodule

test_ternary_mux.v
module test_ter_mux();
reg [1:0] inbit;
reg sbit;
wire ybit;

ternary_mux obj(
.in(inbit),
.s(sbit),
.y(ybit)
);

initial begin
      inbit = 0;  sbit=0;
      #10; inbit = 0; sbit=1;
      #10; inbit = 1; sbit=0;
      #10; inbit = 1; sbit=1;
      #10; inbit = 2; sbit=0;
      #10; inbit = 2; sbit=1;
      #10; inbit = 3; sbit=0;
      #10; inbit = 3; sbit=1;
      #10;
end

initial begin
      $dumpfile("ter_mux.vcd");
      $dumpvars(0,test_ter_mux);
      $monitor("time = %2d,   INPUT=%2b,     S =%1b,    OUT =%1b", $time,inbit,sbit,ybit);
end
endmodule

ter_mux.vcd
$date
	Thu Oct 11 14:48:31 2018
$end
$version
	Icarus Verilog
$end
$timescale
	1s
$end
$scope module test_ter_mux $end
$var wire 1 ! ybit $end
$var reg 2 " inbit [1:0] $end
$var reg 1 # sbit $end
$scope module obj $end
$var wire 2 $ in [1:0] $end
$var wire 1 # s $end
$var wire 1 ! y $end
$upscope $end
$upscope $end
$enddefinitions $end
#0
$dumpvars
b0 $
0#
b0 "
0!
$end
#10
1#
#20
1!
0#
b1 "
b1 $
#30
0!
1#
#40
0#
b10 "
b10 $
#50
1!
1#
#60
0#
b11 "
b11 $
#70
1#
