tran_gate.v
module tran_gate(input a, input ne, input pe, output y);

nmos(y,a,ne);
pmos(y,a,pe);

endmodule

mux_2_1_tran.v
`include "tran_gate.v"

module mux_2_1_tran(input a, input b, input s, output y);
tran_gate o1(.a(a),.ne(~s),.pe(s),.y(y));
tran_gate o2(.a(b),.ne(s),.pe(~s),.y(y));
endmodule

mux_4_1_tran.v
`include "mux_2_1_tran.v"

module mux_4_1_tran(input a, input b, input c, input d, input s0, input s1, output y);
wire w1,w2;
mux_2_1_tran o1(.a(a),.b(b),.s(s0),.y(w1));
mux_2_1_tran o2(.a(c),.b(d),.s(s0),.y(w2));
mux_2_1_tran o3(.a(w1),.b(w2),.s(s1),.y(y));
endmodule

test_mux_4_1_tran.v
module tran_mux_4_1();

reg abit;
reg bbit;
reg cbit;
reg dbit;
reg sel0;
reg sel1;
wire w;

mux_4_1_tran obj(
.a(abit),
.b(bbit),
.c(cbit),
.d(dbit),
.s0(sel0),
.s1(sel1),
.y(w)
);

initial
      begin
            sel0=0;     sel1=0;     abit=0;     bbit=0;     cbit=1;     dbit=1;
            #10;        sel0=0;     sel1=0;          abit=0; bbit=1; cbit=0; dbit=1;
            #10;        sel0=1;     sel1=0;          abit=0; bbit=0; cbit=1; dbit=1;
            #10;        sel0=1;     sel1=0;          abit=0; bbit=1; cbit=0; dbit=1;
            #10;        sel0=0;     sel1=1;          abit=0; bbit=0; cbit=1; dbit=1;
            #10;        sel0=0;     sel1=1;          abit=0; bbit=1; cbit=0; dbit=1;
            #10;        sel0=1;     sel1=1;          abit=0; bbit=0; cbit=1; dbit=1;
            #10;        sel0=1;     sel1=1;          abit=0; bbit=1; cbit=0; dbit=1;
            #20;
      end

initial
  begin
    $dumpfile("tran_mux_4_1.vcd");
    $dumpvars(0,tran_mux_4_1);
    $monitor("time = %2d,      S1(MSB) =%1b, S0 =%1b      A =%1b,   B =%1b,   C =%1b,    D =%1b,    Out =%1b", $time,sel1,sel0,abit,bbit,cbit,dbit,w);
  end
endmodule

tran_mux_4_1.vcd
$date
	Thu Sep 20 16:14:11 2018
$end
$version
	Icarus Verilog
$end
$timescale
	1s
$end
$scope module tran_mux_4_1 $end
$var wire 1 ! w $end
$var reg 1 " abit $end
$var reg 1 # bbit $end
$var reg 1 $ cbit $end
$var reg 1 % dbit $end
$var reg 1 & sel0 $end
$var reg 1 ' sel1 $end
$scope module obj $end
$var wire 1 " a $end
$var wire 1 # b $end
$var wire 1 $ c $end
$var wire 1 % d $end
$var wire 1 & s0 $end
$var wire 1 ' s1 $end
$var wire 1 ( w1 $end
$var wire 1 ) w2 $end
$var wire 1 ! y $end
$scope module o1 $end
$var wire 1 " a $end
$var wire 1 # b $end
$var wire 1 & s $end
$var wire 1 ( y $end
$scope module o1 $end
$var wire 1 " a $end
$var wire 1 * ne $end
$var wire 1 & pe $end
$var wire 1 ( y $end
$upscope $end
$scope module o2 $end
$var wire 1 # a $end
$var wire 1 & ne $end
$var wire 1 + pe $end
$var wire 1 ( y $end
$upscope $end
$upscope $end
$scope module o2 $end
$var wire 1 $ a $end
$var wire 1 % b $end
$var wire 1 & s $end
$var wire 1 ) y $end
$scope module o1 $end
$var wire 1 $ a $end
$var wire 1 , ne $end
$var wire 1 & pe $end
$var wire 1 ) y $end
$upscope $end
$scope module o2 $end
$var wire 1 % a $end
$var wire 1 & ne $end
$var wire 1 - pe $end
$var wire 1 ) y $end
$upscope $end
$upscope $end
$scope module o3 $end
$var wire 1 ( a $end
$var wire 1 ) b $end
$var wire 1 ' s $end
$var wire 1 ! y $end
$scope module o1 $end
$var wire 1 ( a $end
$var wire 1 . ne $end
$var wire 1 ' pe $end
$var wire 1 ! y $end
$upscope $end
$scope module o2 $end
$var wire 1 ) a $end
$var wire 1 ' ne $end
$var wire 1 / pe $end
$var wire 1 ! y $end
$upscope $end
$upscope $end
$upscope $end
$upscope $end
$enddefinitions $end
#0
$dumpvars
1/
1.
1-
1,
1+
1*
1)
0(
0'
0&
1%
1$
0#
0"
0!
$end
#10
0)
0$
1#
#20
0*
0+
0,
0-
1$
0#
0!
0(
1)
1&
#30
0$
1!
1(
1#
#40
0.
0/
1*
1+
1,
1-
1$
0#
1'
1!
0(
1)
0&
#50
0!
0)
0$
1#
#60
0*
0+
0,
0-
1$
0#
0(
1!
1)
1&
#70
0$
1(
1#
