tran_gate.v
module tran_gate(input a, input ne, input pe, output y);

nmos(y,a,ne);
pmos(y,a,pe);

endmodule

mux_2_1_tran.v
`include "tran_gate.v"

module mux_2_1_tran(input a, input b, input s, output y);
tran_gate o1(.a(a),.ne(~s),.pe(s),.y(y));
tran_gate o2(.a(b),.ne(s),.pe(~s),.y(y));
endmodule

test_mux_2_1_tran.v
module tran_mux_2_1();

reg abit;
reg bbit;
wire w;
reg sel;

mux_2_1_tran obj(
.a(abit),
.b(bbit),
.s(sel),
.y(w)
);

initial
      begin
            abit=0;
            bbit=0;
            sel=0;
            #10;        sel=0;          abit=0; bbit=1;
            #10;        sel=0;          abit=1; bbit=0;
            #10;        sel=0;          abit=1; bbit=1;
            #10;        sel=1;          abit=0; bbit=0;
            #10;        sel=1;          abit=1; bbit=0;
            #10;        sel=1;          abit=0; bbit=1;
            #10;        sel=1;          abit=1; bbit=1;
            #20;
      end

initial
  begin
    $dumpfile("tran_mux_2_1.vcd");
    $dumpvars(0,tran_mux_2_1);
    $monitor("time = %2d,      S =%1b,       A =%1b,   B =%1b,    Out =%1b", $time,sel,abit,bbit,w);
  end
endmodule

tran_mux_2_1.vcd
$date
	Thu Sep 20 16:12:29 2018
$end
$version
	Icarus Verilog
$end
$timescale
	1s
$end
$scope module tran_mux_2_1 $end
$var wire 1 ! w $end
$var reg 1 " abit $end
$var reg 1 # bbit $end
$var reg 1 $ sel $end
$scope module obj $end
$var wire 1 " a $end
$var wire 1 # b $end
$var wire 1 $ s $end
$var wire 1 ! y $end
$scope module o1 $end
$var wire 1 " a $end
$var wire 1 % ne $end
$var wire 1 $ pe $end
$var wire 1 ! y $end
$upscope $end
$scope module o2 $end
$var wire 1 # a $end
$var wire 1 $ ne $end
$var wire 1 & pe $end
$var wire 1 ! y $end
$upscope $end
$upscope $end
$upscope $end
$enddefinitions $end
#0
$dumpvars
1&
1%
0$
0#
0"
0!
$end
#10
1#
#20
0#
1!
1"
#30
1#
#40
0%
0&
0#
0!
0"
1$
#50
1"
#60
1!
1#
0"
#70
1"
